{
  "attributes": [
    {
      "default": "nil",
      "size": null,
      "type": "uuid",
      "source": "id",
      "references": null,
      "allow_nil?": false,
      "primary_key?": true,
      "generated?": false
    },
    {
      "default": "nil",
      "size": null,
      "type": "text",
      "source": "relative_path",
      "references": null,
      "allow_nil?": false,
      "primary_key?": false,
      "generated?": false
    },
    {
      "default": "nil",
      "size": null,
      "type": "bigint",
      "source": "change_count_30d",
      "references": null,
      "allow_nil?": false,
      "primary_key?": false,
      "generated?": false
    },
    {
      "default": "nil",
      "size": null,
      "type": "utc_datetime_usec",
      "source": "last_changed_at",
      "references": null,
      "allow_nil?": true,
      "primary_key?": false,
      "generated?": false
    },
    {
      "default": "nil",
      "size": null,
      "type": "float",
      "source": "heat_score",
      "references": null,
      "allow_nil?": false,
      "primary_key?": false,
      "generated?": false
    },
    {
      "default": "nil",
      "size": null,
      "type": "bigint",
      "source": "size_bytes",
      "references": null,
      "allow_nil?": true,
      "primary_key?": false,
      "generated?": false
    },
    {
      "default": "nil",
      "size": null,
      "type": "bigint",
      "source": "loc",
      "references": null,
      "allow_nil?": true,
      "primary_key?": false,
      "generated?": false
    },
    {
      "default": "nil",
      "size": null,
      "type": "utc_datetime_usec",
      "source": "inserted_at",
      "references": null,
      "allow_nil?": false,
      "primary_key?": false,
      "generated?": false
    },
    {
      "default": "nil",
      "size": null,
      "type": "utc_datetime_usec",
      "source": "updated_at",
      "references": null,
      "allow_nil?": false,
      "primary_key?": false,
      "generated?": false
    },
    {
      "default": "nil",
      "size": null,
      "type": "uuid",
      "source": "project_id",
      "references": {
        "name": "file_heatmaps_project_id_fkey",
        "table": "projects",
        "multitenancy": {
          "global": null,
          "attribute": null,
          "strategy": null
        },
        "primary_key?": true,
        "destination_attribute": "id",
        "on_delete": null,
        "on_update": null,
        "deferrable": false,
        "destination_attribute_generated": null,
        "destination_attribute_default": null
      },
      "allow_nil?": false,
      "primary_key?": false,
      "generated?": false
    }
  ],
  "table": "file_heatmaps",
  "hash": "60EC8E94047C54A399E180A29C8C1CBB5C5C2F85E92C951F0EFFFD4009252111",
  "repo": "Elixir.Spotter.Repo",
  "multitenancy": {
    "global": null,
    "attribute": null,
    "strategy": null
  },
  "identities": [
    {
      "name": "unique_project_path",
      "keys": [
        "project_id",
        "relative_path"
      ],
      "base_filter": null,
      "index_name": "file_heatmaps_unique_project_path_index"
    }
  ],
  "strict?": false,
  "custom_indexes": [],
  "base_filter": null,
  "custom_statements": [],
  "has_create_action": true
}